{
    "$schema": "https://schema.management.azure.com/schemas/2015-01-01/deploymentParameters.json#",
    "contentVersion": "1.0.0.0",
    "parameters": {
        "subscriptionId": {
            "value": "3cb9b5fa-ea8d-414d-8dcc-f8c70d6b0677"
        },
        "name": {
            "value": "IaC-musicstore-pl"
        },
        "location": {
            "value": "South India"
        },
        "hostingEnvironment": {
            "value": ""
        },
        "hostingPlanName": {
            "value": "ASP-KarthikResourceGroup-babf"
        },
        "serverFarmResourceGroup": {
            "value": "KarthikResourceGroup"
        },
        "alwaysOn": {
            "value": false
        },
        "currentStack": {
            "value": "dotnet"
        },
        "netFrameworkVersion": {
            "value": "v4.0"
        }
    }
}
